[
  {
    "title": "Bad Moon Rising",
    "file": "scripts/Bad-Moon-Rising.png",
    "json": "scripts/Bad-Moon-Rising.json",
    "current": false
  },
  {
    "title": "Damsel In Distress",
    "file": "scripts/Damsel-in-Distress.png",
    "json": "scripts/Damsel-in-Distress.json",
    "current": false
  },
  {
    "title": "Idiots Idiots Idiots",
    "file": "scripts/Idiots-Idiots-Idiots.png",
    "json": "scripts/Idiots-Idiots-Idiots.json",
    "current": false
  },
  {
    "title": "Is The Town Lying",
    "file": "scripts/Is-the-town-lying.png",
    "json": "scripts/Is-the-town-lying.json",
    "current": false
  },
  {
    "title": "One Yes Is Enough",
    "file": "scripts/One-Yes-Is-Enough.png",
    "json": "scripts/One-Yes-Is-Enough.json",
    "current": false
  },
  {
    "title": "Open Season",
    "file": "scripts/Open-Season.png",
    "json": "scripts/Open-Season.json",
    "current": false
  },
  {
    "title": "The Bloody Harvest",
    "file": "scripts/The-Bloody-Harvest.png",
    "json": "scripts/The-Bloody-Harvest.json",
    "current": false
  },
  {
    "title": "Trouble Brewing Reforged",
    "file": "scripts/Trouble-Brewing-Reforged.png",
    "json": "scripts/Trouble-Brewing-Reforged.json",
    "current": false
  },
  {
    "title": "Trouble Brewing",
    "file": "scripts/Trouble-Brewing.png",
    "json": "scripts/Trouble-Brewing.json",
    "current": false
  },
  {
    "title": "Twisted Truths",
    "file": "scripts/Twisted-Truths.png",
    "json": "scripts/Twisted-Truths.json",
    "current": false
  },
  {
    "title": "Unknown Townsfolk",
    "file": "scripts/Unknown-townsfolk.png",
    "json": "scripts/Unknown-townsfolk.json",
    "current": false
  },
  {
    "title": "Circus",
    "file": "scripts/circus.png",
    "json": null,
    "current": false
  }
]
